flem/__init__.py
flem/__main__.py
flem/config.json
flem/py.typed
flem/animator_files/battery/charging.json
flem/animator_files/weather/clear.json
flem/animator_files/weather/cloud_rain.json
flem/animator_files/weather/cloud_storm.json
flem/animator_files/weather/cloudy.json
flem/animator_files/weather/fog.json
flem/animator_files/weather/snowflake.json
flem/cli/README.md
flem/cli/__init__.py
flem/cli/flem_config.py
flem/cli/flem_device.py
flem/cli/flem_service.py
flem/cli/flem_tool.py
flem/cli/click/custom_group.py
flem/devices/__init__.py
flem/devices/led_device.py
flem/matrix/__init__.py
flem/matrix/matrix.py
flem/matrix/scene.py
flem/models/__init__.py
flem/models/config.py
flem/models/config_schema.py
flem/models/modules/__init__.py
flem/models/modules/animator_config.py
flem/models/modules/battery_config.py
flem/models/modules/clock_config.py
flem/models/modules/cpu_config.py
flem/models/modules/gpu_config.py
flem/models/modules/line_config.py
flem/models/modules/weather_config.py
flem/modules/README.MD
flem/modules/__init__.py
flem/modules/animator_module.py
flem/modules/battery_module.py
flem/modules/binary_clock_module.py
flem/modules/clock_module.py
flem/modules/cpu_h_module.py
flem/modules/cpu_module.py
flem/modules/gpu_h_module.py
flem/modules/gpu_module.py
flem/modules/line_module.py
flem/modules/matrix_module.py
flem/modules/ram_module.py
flem/modules/weather_module.py
flem/modules/utilities/characters.py
flem/scripts/install_flem_service.sh
flem/scripts/uninstall_flem_service.sh
flem/utilities/__init__.py
flem/utilities/utilities.py
flem_tool-0.3.3.dist-info/METADATA
flem_tool-0.3.3.dist-info/WHEEL
flem_tool-0.3.3.dist-info/entry_points.txt
flem_tool-0.3.3.dist-info/licenses/LICENSE
flem_tool-0.3.3.dist-info/RECORD
