Metadata-Version: 2.4
Name: flem_tool
Version: 0.3.3
Summary: Utility for managing the Framework LED Matrix Input Module
Project-URL: Home, https://github.com/jwilkins88/flem_tool
Author: Joel Wilkins
License-Expression: GPL-3.0-or-later
License-File: LICENSE
Requires-Python: >=3.9
Requires-Dist: click>=8.0.3
Requires-Dist: loguru>=0.7.3
Requires-Dist: marshmallow>=3.26.1
Requires-Dist: packaging>=24.2
Requires-Dist: psutil>=7.0.0
Requires-Dist: pyserial>=3.5
Requires-Dist: requests>=2.32.3
